{"charas":[{"id":1,"name":"aaaaaaaa","title":"","player_name":"teru","skill_total":0,"specialty_total":0,"script":"","skills":[{"id":1,"value":0,"checked":false},{"id":2,"value":0,"checked":false},{"id":3,"value":0,"checked":false},{"id":4,"value":0,"checked":false},{"id":5,"value":0,"checked":false},{"id":6,"value":0,"checked":false},{"id":7,"value":0,"checked":false},{"id":8,"value":0,"checked":false},{"id":9,"value":0,"checked":false}],"specialties":[{"id":1,"value":0,"checked":false},{"id":2,"value":0,"checked":false},{"id":3,"value":0,"checked":false},{"id":4,"value":0,"checked":false},{"id":5,"value":0,"checked":false},{"id":6,"value":0,"checked":false},{"id":7,"value":0,"checked":false},{"id":8,"value":0,"checked":false},{"id":9,"value":0,"checked":false},{"id":10,"value":0,"checked":false},{"id":11,"value":0,"checked":false},{"id":12,"value":0,"checked":false}],"damages":[{"value":1,"checked":false},{"value":2,"checked":false},{"value":3,"checked":false}]}]}